{
    "root_group": {
        "name": "",
        "path": "",
        "id": "d41d8cd98f00b204e9800998ecf8427e",
        "groups": {},
        "checks": {
                "200 OK": {
                    "name": "200 OK",
                    "path": "::200 OK",
                    "id": "e9654c443eff553da9e69eda7007924e",
                    "passes": 9901,
                    "fails": 99
                },
                "201 Created": {
                    "path": "::201 Created",
                    "id": "728dcd977aae263ca314731145e1d447",
                    "passes": 0,
                    "fails": 10000,
                    "name": "201 Created"
                },
                "204 No Content": {
                    "name": "204 No Content",
                    "path": "::204 No Content",
                    "id": "54fa3c2eda34e1622fda2da5e0479fc5",
                    "passes": 0,
                    "fails": 10000
                },
                "400 Bad Request": {
                    "fails": 10000,
                    "name": "400 Bad Request",
                    "path": "::400 Bad Request",
                    "id": "eeae81934b9b58bccaf0184a6d070338",
                    "passes": 0
                },
                "401 Unauthorized": {
                    "path": "::401 Unauthorized",
                    "id": "6ae9254e6aefe7f0bafe5102fa7e20a5",
                    "passes": 0,
                    "fails": 10000,
                    "name": "401 Unauthorized"
                },
                "403 Forbidden": {
                    "name": "403 Forbidden",
                    "path": "::403 Forbidden",
                    "id": "655548b761742c5a7ad15aa7df3a5d9c",
                    "passes": 0,
                    "fails": 10000
                },
                "404 Not Found": {
                    "name": "404 Not Found",
                    "path": "::404 Not Found",
                    "id": "df1528f9925ca236bac51008f77b774a",
                    "passes": 0,
                    "fails": 10000
                },
                "429 Too Many Requests": {
                    "name": "429 Too Many Requests",
                    "path": "::429 Too Many Requests",
                    "id": "b810c35b9499cc7342fd415032e3a6aa",
                    "passes": 0,
                    "fails": 10000
                },
                "500 Internal Server Error": {
                    "name": "500 Internal Server Error",
                    "path": "::500 Internal Server Error",
                    "id": "3cd96245b24e869810efe46d533b0eef",
                    "passes": 0,
                    "fails": 10000
                },
                "502 Bad Gateway": {
                    "fails": 10000,
                    "name": "502 Bad Gateway",
                    "path": "::502 Bad Gateway",
                    "id": "712cb0ec189a11f31f0d6d0c0031b569",
                    "passes": 0
                },
                "503 Service Unavailable": {
                    "name": "503 Service Unavailable",
                    "path": "::503 Service Unavailable",
                    "id": "f1ea1a22be0dc738c385523a66ea1cd9",
                    "passes": 0,
                    "fails": 10000
                },
                "504 Gateway Timeout": {
                    "passes": 0,
                    "fails": 10000,
                    "name": "504 Gateway Timeout",
                    "path": "::504 Gateway Timeout",
                    "id": "218efb729cb654723ccd57c6ebbebe29"
                }
            }
    },
    "metrics": {
        "iteration_duration": {
            "p(90)": 19495.58553,
            "p(95)": 20100.319535,
            "avg": 16045.016907650035,
            "min": 1722.1806,
            "med": 16916.472950000003,
            "max": 61012.4271
        },
        "http_req_sending": {
            "med": 0,
            "max": 66.2937,
            "p(90)": 1.0021,
            "p(95)": 1.4656699999999931,
            "avg": 0.5361647200000002,
            "min": 0
        },
        "http_req_duration{expected_response:true}": {
            "avg": 9820.739204524783,
            "min": 43.1587,
            "med": 9699.8053,
            "max": 49174.5315,
            "p(90)": 16432.8859,
            "p(95)": 17690.4554
        },
        "vus": {
            "value": 33,
            "min": 0,
            "max": 10000
        },
        "vus_max": {
            "value": 10000,
            "min": 3945,
            "max": 10000
        },
        "http_req_blocked": {
            "p(95)": 10639.45473,
            "avg": 5009.683896040001,
            "min": 0,
            "med": 5409.133400000001,
            "max": 31279.2243,
            "p(90)": 8219.24105
        },
        "http_req_connecting": {
            "med": 2578.5401,
            "max": 10211.8401,
            "p(90)": 2903.8548100000003,
            "p(95)": 3043.0646,
            "avg": 2002.3766318200003,
            "min": 27.9986
        },
        "data_sent": {
            "count": 37724098,
            "rate": 616210.3465633355
        },
        "http_reqs": {
            "count": 10000,
            "rate": 163.34660846319917
        },
        "http_req_waiting": {
            "avg": 2889.670643570006,
            "min": 0,
            "med": 2105.06465,
            "max": 33739.1202,
            "p(90)": 6307.26598,
            "p(95)": 7503.146395000001
        },
        "http_req_receiving": {
            "p(90)": 14064.192500000001,
            "p(95)": 16077.538109999998,
            "avg": 6833.307078110023,
            "min": 0,
            "med": 5872.2296,
            "max": 43094.8653
        },
        "http_req_tls_handshaking": {
            "avg": 3035.912736839991,
            "min": 0,
            "med": 2742.3388999999997,
            "max": 28486.4379,
            "p(90)": 5534.197170000002,
            "p(95)": 8026.956594999995
        },
        "http_req_duration": {
            "avg": 9723.51388639999,
            "min": 0,
            "med": 9648.06095,
            "max": 49174.5315,
            "p(90)": 16420.30928,
            "p(95)": 17678.952185
        },
        "iterations": {
            "count": 10000,
            "rate": 163.34660846319917
        },
        "http_req_failed": {
            "passes": 99,
            "fails": 9901,
            "value": 0.0099
        },
        "data_received": {
            "count": 5358536295,
            "rate": 87529873.01152068
        },
        "checks": {
            "passes": 9901,
            "fails": 110099,
            "value": 0.08250833333333334
        }
    }
}